README.md
setup.py
pygol/__init__.py
pygol/gameoflife.py
pygol.egg-info/PKG-INFO
pygol.egg-info/SOURCES.txt
pygol.egg-info/dependency_links.txt
pygol.egg-info/top_level.txt