Metadata-Version: 2.1
Name: pygol
Version: 1.0
Summary: Conway's Game of Life, made with tkinter
Home-page: https://github.com/stefandevries94/GameOfLife.git
Author: stefan94
Author-email: stefandevries94@gmail.com
License: UNKNOWN
Platform: UNKNOWN
Classifier: Programming Language :: Python :: 3
Classifier: License :: OSI Approved :: MIT License
Classifier: Operating System :: OS Independent
